README.md
setup.py
ceotr_kml_tool.egg-info/PKG-INFO
ceotr_kml_tool.egg-info/SOURCES.txt
ceotr_kml_tool.egg-info/dependency_links.txt
ceotr_kml_tool.egg-info/requires.txt
ceotr_kml_tool.egg-info/top_level.txt
kml_tool/__init__.py
kml_tool/compare.py
kml_tool/erddap_kml_generator.py
kml_tool/models.py
kml_tool/sfmc_kml_generator.py
kml_tool/wave_kml_generator.py
kml_tool/ref/GEstyle.txt
kml_tool/res/__init__.py