Metadata-Version: 2.1
Name: ceotr-kml-tool
Version: 1.0.0
Summary: library tool to download and process KML files from SFMC
Home-page: https://gitlab.oceantrack.org/ceotr/gliders/kml_tool
Author: CEOTR
Classifier: Programming Language :: Python :: 3
Classifier: Operating System :: OS Independent
Requires-Python: >=3.6
Requires-Dist: bs4
Requires-Dist: pykml
